s/__init__.py
s/altall.py
s/fbsingle.py
s/goimg.py
s/instaall.py
s/instasingle.py
s/trading_image.py
s/twsingle.py
s/wpmsg.py
scrapper/__init__.py
scrapper/altall.py
scrapper/fbsingle.py
scrapper/goimg.py
scrapper/instaall.py
scrapper/instasingle.py
scrapper/scrape.py
scrapper/trading_image.py
scrapper/twsingle.py
scrapper/wpmsg.py
scrapeShivam-2.0.0.dist-info/LICENSE
scrapeShivam-2.0.0.dist-info/METADATA
scrapeShivam-2.0.0.dist-info/WHEEL
scrapeShivam-2.0.0.dist-info/top_level.txt
scrapeShivam-2.0.0.dist-info/RECORD
