Metadata-Version: 2.1
Name: scrapeShivam
Version: 2.0.0
Summary: Scrapping altnews|Google images|Instagram|facebook|Twitter|Tradingview chartImage
Home-page: https://github.com/sv6375261073/scrapperSV
Author: Shivam Vishwakarma
Author-email: sv6375261073@gmail.com
License: MIT
Platform: UNKNOWN
Classifier: Programming Language :: Python :: 3
Classifier: License :: OSI Approved :: MIT License
Classifier: Operating System :: OS Independent
Requires-Python: >=3.6
Requires-Dist: requests
Requires-Dist: beautifulsoup4 (==4.9.2)
Requires-Dist: imageio (==2.9.0)
Requires-Dist: lxml (==4.5.2)
Requires-Dist: matplotlib
Requires-Dist: numpy
Requires-Dist: pandas
Requires-Dist: Pillow (==7.2.0)
Requires-Dist: selenium (==3.141.0)
